{
 "attack": "ATK 3200",
 "attribute": "地",
 "defence": "DEF 2800",
 "description": "「アマゾネス」融合モンスター＋「アマゾネス」モンスター\u000aこのカード名の(1)の効果は１ターンに１度しか使用できない。\u000a(1)：このカードが融合召喚に成功した場合に発動できる。デッキから「アマゾネス」モンスター１体を特殊召喚する。\u000a(2)：このカードがモンスターゾーンに存在する限り、このカード以外の自分フィールドの「アマゾネス」カードは相手の効果の対象にならず、相手の効果では破壊されない。\u000a(3)：「アマゾネス女帝」または「アマゾネス女王」を素材として融合召喚したこのカードは１度のバトルフェイズ中に２回攻撃できる。",
 "kinds": [
  {
   "kind": "効果"
  },
  {
   "kind": "融合"
  }
 ],
 "level": 10,
 "name": "アマゾネス女帝王",
 "pronunciation": "アマゾネスカイゼリン",
 "race": "戦士"
}