{
 "attack": "2400",
 "attribute": "闇",
 "description": "トークン以外のモンスター２体以上\u000a(1)：１ターンに１度、ダメージステップにモンスターの効果・魔法・罠カードが発動した時に発動できる。その発動を無効にする。\u000a(2)：このカードが守備表示モンスターを攻撃した場合、その守備力を攻撃力が超えた分だけ戦闘ダメージを与える。\u000a(3)：このカードをリリースし、自分の墓地のリンク２以下のモンスター１体を対象として発動できる。そのモンスターを特殊召喚する。その後、手札からレベル４以下のドラゴン族モンスター１体を特殊召喚できる。この効果はこのカードが特殊召喚したターンには発動できない。",
 "kinds": [
  {
   "kind": "効果"
  },
  {
   "kind": "リンク"
  }
 ],
 "link": {
  "arrows": [
   "Up",
   "Low",
   "Left"
  ]
 },
 "name": "スリーバーストショット・ドラゴン",
 "pronunciation": "スリーバーストショット・ドラゴン",
 "race": "ドラゴン"
}