{
 "attack": "1400",
 "attribute": "地",
 "defence": "700",
 "description": "このカード名の(1)(2)(3)の効果はそれぞれ１ターンに１度しか使用できない。\u000a(1)：このカードが召喚・特殊召喚に成功した場合に発動できる。デッキから「ナチュル」カード１枚を墓地へ送る。\u000a(2)：このカードがモンスターゾーンに存在する限り、自分が「ナチュル」モンスターの効果を発動するためにモンスターをリリースする場合、代わりに自分のデッキの上からカードを２枚墓地へ送る事ができる。\u000a(3)：相手がモンスターの召喚・特殊召喚に成功した場合に発動できる。自分の墓地から「ナチュル」モンスター１体を選んで特殊召喚する。",
 "kinds": [
  {
   "kind": "効果"
  },
  {
   "kind": "チューナー"
  }
 ],
 "level": 4,
 "name": "ナチュル・カメリア",
 "pronunciation": "ナチュル・カメリア",
 "race": "植物"
}