{
 "attack": "3000",
 "attribute": "闇",
 "defence": "2600",
 "description": "「ムーンライト」モンスター×３\u000aこのカードは融合召喚でしか特殊召喚できない。このカード名の(3)の効果は１ターンに１度しか使用できない。\u000a(1)：このカードの攻撃力は、お互いの墓地の獣戦士族モンスター及び除外されている獣戦士族モンスターの数×２００アップする。\u000a(2)：このカードは相手の効果の対象にならない。\u000a(3)：墓地のこのカードを除外し、自分フィールドの融合モンスター１体を対象として発動できる。そのモンスターの攻撃力はターン終了時まで３０００アップする。この効果はこのカードが墓地へ送られたターンには発動できない。",
 "kinds": [
  {
   "kind": "効果"
  },
  {
   "kind": "融合"
  }
 ],
 "level": 9,
 "name": "月光舞剣虎姫",
 "pronunciation": "ムーンライトサーベルダンサー",
 "race": "獣戦士"
}