{
 "attack": "3000",
 "attribute": "闇",
 "defence": "3000",
 "description": "【Ｐスケール：青１０\/赤１０】\u000aこのカード名のＰ効果は１ターンに１度しか使用できない。\u000a(1)：相手のＰゾーンのカード１枚を対象として発動できる。このカードを特殊召喚し、対象のカードを自分のＰゾーンに置く。この効果で置いたカードは次のターンのエンドフェイズに破壊される。\u000a【モンスター効果】\u000aこのカードは通常召喚できず、このカードの効果でのみ特殊召喚できる。\u000a(1)：自分がモンスターをＰ召喚した時、自分のＰゾーンのＰスケールの合計がＰ召喚したモンスターのレベルの合計を超えていれば発動できる。このカードを手札から特殊召喚し、フィールドの他のカードを全て破壊する。その後、このカードを自分のＰゾーンに置く事ができる。\u000a(2)：１ターンに１度、自分フィールドの他の表側表示の「ＤＤＤ」モンスターが魔法カードの効果でフィールドから離れた場合に発動する。このカードの攻撃力は６０００になる。",
 "kinds": [
  {
   "kind": "効果"
  },
  {
   "kind": "ペンデュラム"
  }
 ],
 "level": 12,
 "name": "ＤＤＤＤ超次元統皇ゼロ・パラドックス",
 "pronunciation": "ディーディーディーディーチョウジゲントウオウゼロパラドックス",
 "race": "悪魔"
}