{
 "attack": "500",
 "attribute": "風",
 "defence": "1000",
 "description": "チューナー＋チューナー以外のモンスター１体以上\u000aこのカード名の効果は１ターンに１度しか使用できず、この効果を発動するターン、自分は風属性モンスターしか特殊召喚できない。\u000a(1)：このカードがＳ召喚に成功した場合、以下の効果から１つを選択して発動できる。\u000a●デッキから「スピードロイド」魔法・罠カード１枚を手札に加える。\u000a●このカードが「スピードロイド」モンスターのみを素材としてＳ召喚していた場合、そのＳ召喚に使用したＳ素材モンスター一組が全て自分の墓地に揃っていれば、その一組を特殊召喚する。",
 "kinds": [
  {
   "kind": "効果"
  },
  {
   "kind": "チューナー"
  },
  {
   "kind": "シンクロ"
  }
 ],
 "level": 3,
 "name": "ＨＳＲコルク－１０",
 "pronunciation": "ハイスピードロイドコルクジュウ",
 "race": "機械"
}