{
 "attack": "2500",
 "attribute": "光",
 "defence": "2000",
 "description": "Ｘ素材を持った同じランクの「Ｎｏ.」Ｘモンスター×２体以上\u000a(1)：１ターンに１度、自分メインフェイズに発動できる。このカードのＸ素材の種類の数まで、エクストラデッキからランク９以下で攻撃力３０００以下の「Ｎｏ.」モンスターを効果を無効にして特殊召喚する（同じランクは１体まで）。その後、このカードのＸ素材を１つ取り除く。このターン、相手が受ける戦闘ダメージは半分になり、自分はモンスターを特殊召喚できない。\u000a(2)：自分フィールドに他の「Ｎｏ.」Ｘモンスターが存在する限り、このカードは戦闘・効果では破壊されない。",
 "kinds": [
  {
   "kind": "効果"
  },
  {
   "kind": "エクシーズ"
  }
 ],
 "name": "Ｎｏ.９３ 希望皇ホープ・カイザー",
 "pronunciation": "ナンバーズキュウジュウサンキボウオウホープカイザー",
 "race": "戦士",
 "rank": 12
}